<?xml version="1.0" encoding="UTF-8"?>
<itop_design xmlns:xsi="http://www.w3.org/2001/XMLSchema-instance" version="1.0">
	<classes>
	</classes>
	<menus>
		<menu id="CustomerSurvey" xsi:type="TemplateMenuNode" _delta="define">
			<rank>50</rank>
			<parent>RequestManagement</parent>
		</menu>
		<menu id="Quizzes" xsi:type="OQLMenuNode" _delta="define">
			<rank>1</rank>
			<parent>CustomerSurvey</parent>
			<oql>SELECT Quizz</oql>
			<do_search>1</do_search>
		</menu>
		<menu id="Surveys" xsi:type="OQLMenuNode" _delta="define">
			<rank>2</rank>
			<parent>CustomerSurvey</parent>
			<oql>SELECT Survey</oql>
			<do_search>1</do_search>
		</menu>
	</menus>
</itop_design>
